{
  "name": "chartbeat-mdadm",
  "version": "2.0.2",
  "author": "chartbeat",
  "summary": "Module to manage mdadm",
  "license": "MIT",
  "source": "https://github.com/chartbeat-labs/puppet-mdadm",
  "project_page": "https://github.com/chartbeat-labs/puppet-mdadm",
  "issues_url": "https://github.com/chartbeat-labs/puppet-mdadm/issues",
  "dependencies": [

  ],
  "operatingsystem_support": [
    {
      "operatingsystem": "Debian",
      "operatingsystemrelease": [
        "6",
        "7",
        "8",
        "9",
        "10"
      ]
    },
    {
      "operatingsystem": "Ubuntu",
      "operatingsystemrelease": [
        "10.04",
        "12.04",
        "16.04",
        "18.04"
      ]
    }
  ],
  "requirements": [
    {
      "name": "puppet",
      "version_requirement": ">= 6.21.0 < 8.0.0"
    }
  ],
  "description": "Mdadm module for Puppet",
  "pdk-version": "2.1.1",
  "template-url": "https://github.com/puppetlabs/pdk-templates#2.1.1",
  "template-ref": "tags/2.1.1-0-g03daa92"
}
